.bumpversion.cfg
.coveragerc
.gitignore
.travis.yml
LICENSE
MANIFEST.in
README.rst
requirements-dev.txt
requirements.txt
setup.py
tox.ini
bioinfo/__init__.py
bioinfo/bam_coverage.py
bioinfo.egg-info/PKG-INFO
bioinfo.egg-info/SOURCES.txt
bioinfo.egg-info/dependency_links.txt
bioinfo.egg-info/entry_points.txt
bioinfo.egg-info/not-zip-safe
bioinfo.egg-info/requires.txt
bioinfo.egg-info/top_level.txt
tests/test_bioinfo.py
tests/data/bam_align.sorted.bam
tests/data/bam_gen.txt
tests/data/bam_query.fasta
tests/data/bam_ref.fasta