Metadata-Version: 1.1
Name: bioinfo
Version: 0.1.4
Summary: Bioinformatics scripts
Home-page: https://github.com/luizirber/bioinfo
Author: Luiz Irber
Author-email: luiz@luizirber.org
License: Copyright (c) 2014, Michigan State University. All rights reserved.
